chainer_chemistry/__init__.py
chainer_chemistry/_version.py
chainer_chemistry/config.py
chainer_chemistry/dataset/__init__.py
chainer_chemistry/dataset/indexer.py
chainer_chemistry/dataset/utils.py
chainer_chemistry/dataset/converters/__init__.py
chainer_chemistry/dataset/converters/cgcnn_converter.py
chainer_chemistry/dataset/converters/concat_mols.py
chainer_chemistry/dataset/converters/megnet_converter.py
chainer_chemistry/dataset/graph_dataset/__init__.py
chainer_chemistry/dataset/graph_dataset/base_graph_data.py
chainer_chemistry/dataset/graph_dataset/base_graph_dataset.py
chainer_chemistry/dataset/graph_dataset/feature_converters.py
chainer_chemistry/dataset/indexers/__init__.py
chainer_chemistry/dataset/indexers/numpy_tuple_dataset_feature_indexer.py
chainer_chemistry/dataset/parsers/__init__.py
chainer_chemistry/dataset/parsers/base_parser.py
chainer_chemistry/dataset/parsers/csv_file_parser.py
chainer_chemistry/dataset/parsers/data_frame_parser.py
chainer_chemistry/dataset/parsers/sdf_file_parser.py
chainer_chemistry/dataset/parsers/smiles_parser.py
chainer_chemistry/dataset/preprocessors/__init__.py
chainer_chemistry/dataset/preprocessors/atomic_number_preprocessor.py
chainer_chemistry/dataset/preprocessors/base_preprocessor.py
chainer_chemistry/dataset/preprocessors/cgcnn_preprocessor.py
chainer_chemistry/dataset/preprocessors/common.py
chainer_chemistry/dataset/preprocessors/ecfp_preprocessor.py
chainer_chemistry/dataset/preprocessors/ggnn_preprocessor.py
chainer_chemistry/dataset/preprocessors/gin_preprocessor.py
chainer_chemistry/dataset/preprocessors/gnnfilm_preprocessor.py
chainer_chemistry/dataset/preprocessors/gwm_preprocessor.py
chainer_chemistry/dataset/preprocessors/megnet_preprocessor.py
chainer_chemistry/dataset/preprocessors/mol_preprocessor.py
chainer_chemistry/dataset/preprocessors/nfp_preprocessor.py
chainer_chemistry/dataset/preprocessors/relgat_preprocessor.py
chainer_chemistry/dataset/preprocessors/relgcn_preprocessor.py
chainer_chemistry-0.7.1.dist-info/LICENSE
chainer_chemistry-0.7.1.dist-info/METADATA
chainer_chemistry-0.7.1.dist-info/WHEEL
chainer_chemistry-0.7.1.dist-info/top_level.txt
chainer_chemistry-0.7.1.dist-info/RECORD
